odoo/addons/report_csv/README.rst
odoo/addons/report_csv/__init__.py
odoo/addons/report_csv/__manifest__.py
odoo/addons/report_csv/controllers/__init__.py
odoo/addons/report_csv/controllers/main.py
odoo/addons/report_csv/demo/report.xml
odoo/addons/report_csv/i18n/es.po
odoo/addons/report_csv/i18n/it.po
odoo/addons/report_csv/i18n/pt_BR.po
odoo/addons/report_csv/i18n/report_csv.pot
odoo/addons/report_csv/models/__init__.py
odoo/addons/report_csv/models/ir_report.py
odoo/addons/report_csv/readme/CONFIGURE.md
odoo/addons/report_csv/readme/CONTRIBUTORS.md
odoo/addons/report_csv/readme/DESCRIPTION.md
odoo/addons/report_csv/readme/USAGE.md
odoo/addons/report_csv/report/__init__.py
odoo/addons/report_csv/report/report_csv.py
odoo/addons/report_csv/report/report_partner_csv.py
odoo/addons/report_csv/static/description/icon.png
odoo/addons/report_csv/static/description/index.html
odoo/addons/report_csv/static/src/js/report/qwebactionmanager.esm.js
odoo/addons/report_csv/tests/__init__.py
odoo/addons/report_csv/tests/test_report.py
odoo/addons/report_csv/views/ir_actions_views.xml
odoo_addon_report_csv-18.0.1.0.0.3.dist-info/METADATA
odoo_addon_report_csv-18.0.1.0.0.3.dist-info/WHEEL
odoo_addon_report_csv-18.0.1.0.0.3.dist-info/top_level.txt
odoo_addon_report_csv-18.0.1.0.0.3.dist-info/RECORD
