Metadata-Version: 2.1
Name: odoo-addon-report_csv
Version: 18.0.1.0.0.3
Requires-Python: >=3.10
Requires-Dist: odoo==18.0.*
Summary: Base module to create csv report
Home-page: https://github.com/OCA/reporting-engine
License: AGPL-3
Author: Creu Blanca, Odoo Community Association (OCA)
Author-email: support@odoo-community.org
Classifier: Programming Language :: Python
Classifier: Framework :: Odoo
Classifier: Framework :: Odoo :: 18.0
Classifier: License :: OSI Approved :: GNU Affero General Public License v3
Classifier: Development Status :: 5 - Production/Stable
